dflogger/__init__.py
dflogger/logger.py
dflogger-0.1.3.dist-info/LICENSE
dflogger-0.1.3.dist-info/METADATA
dflogger-0.1.3.dist-info/WHEEL
dflogger-0.1.3.dist-info/top_level.txt
dflogger-0.1.3.dist-info/RECORD
