Metadata-Version: 2.1
Name: dflogger
Version: 0.1.3
Summary: small and dataframe based machine learning experiment logger
Author: Sulthan Abiyyu
License: MIT
License-File: LICENSE
